<?xml version='1.0' encoding='utf-8'?>
<record xmlns="http://www.openarchives.org/OAI/2.0/" xmlns:xsi="http://www.w3.org/2001/XMLSchema-instance">
			<header>
				<identifier>oai:regsci-ojs-tamu.tdl.org:article/111</identifier>
				<datestamp>2023-04-11T02:11:48Z</datestamp>
				<setSpec>regsci:PC</setSpec>
			</header>
			<metadata>
<oai_dc:dc xmlns:oai_dc="http://www.openarchives.org/OAI/2.0/oai_dc/" xmlns:dc="http://purl.org/dc/elements/1.1/" xmlns:xsi="http://www.w3.org/2001/XMLSchema-instance" xsi:schemaLocation="http://www.openarchives.org/OAI/2.0/oai_dc/  http://www.openarchives.org/OAI/2.0/oai_dc.xsd">
	<dc:title xml:lang="en">Evolution of Directive (EC) No 128/2009 of the European Parliament and of the Council Establishing a Framework for Community Action to Achieve the Sustainable Use of Pesticides</dc:title>
	<dc:creator xml:lang="en">Marchand, Patrice A.</dc:creator>
	<dc:creator xml:lang="en">Robin, Diane</dc:creator>
	<dc:subject xml:lang="en">phytopharmaceuticals</dc:subject>
	<dc:subject xml:lang="en">Directive (EC) No 128/2009</dc:subject>
	<dc:subject xml:lang="en">Regulation (EC) No 1107/2009</dc:subject>
	<dc:subject xml:lang="en">integrated pest management</dc:subject>
	<dc:subject xml:lang="en">sustainable use</dc:subject>
	<dc:subject xml:lang="en">Pesticides</dc:subject>
	<dc:description xml:lang="en">The EC Directive No 128/2009 established a regulatory framework for Community action to achieve the sustainable use of pesticides (phytopharmaceuticals) that entered into force in 2011. The Directive manages all aspect of pesticides approved under Regulation (EC) No 1107/2009 and listed in implementing Regulation (EU) No 540/2011 outside the approval and approval procedure, including all relevant National Action Plans (NAP), training, sales of pesticides, information awareness-raising, pesticides storage, application and equipment (i.e. inspection of equipment in use), specific practices and uses (i.e. aerial spraying), indicators and reporting on pesticide uses. This study examines the evolution of these dispositions framing the use of pesticides in Europe and the recent implementation of the harmonized risk indicators (HRI), which are expected to diminish in numbers over time. Calculation of the annual HRI values, and analysis of their evolution through the years is, therefore, for the first time, a method to quantify the evolution of the theoretical impact of pesticides at the pan-European level and to measure the progress against the original purpose of the directive, and therefore, its success.
https://www.doi.org/10.21423/jrs-v07marchand</dc:description>
	<dc:publisher xml:lang="en">Office of the Texas State Chemist</dc:publisher>
	<dc:date>2019-12-12</dc:date>
	<dc:type>info:eu-repo/semantics/article</dc:type>
	<dc:type>info:eu-repo/semantics/publishedVersion</dc:type>
	<dc:format>application/pdf</dc:format>
	<dc:identifier>https://regsci-ojs-tamu.tdl.org/regsci/article/view/111</dc:identifier>
	<dc:identifier>10.21423/JRS-V07MARCHAND</dc:identifier>
	<dc:source xml:lang="en">Journal of Regulatory Science; Vol 7 (2019); 1-7</dc:source>
	<dc:source>2377-3537</dc:source>
	<dc:language>eng</dc:language>
	<dc:relation>https://regsci-ojs-tamu.tdl.org/regsci/article/view/111/183</dc:relation>
	<dc:rights xml:lang="en">Copyright (c) 2019 Journal of Regulatory Science</dc:rights>
	<dc:rights xml:lang="en">https://creativecommons.org/licenses/by-nc/4.0</dc:rights>
</oai_dc:dc>
			</metadata>
		</record>
		
