<?xml version='1.0' encoding='utf-8'?>
<record xmlns="http://www.openarchives.org/OAI/2.0/" xmlns:xsi="http://www.w3.org/2001/XMLSchema-instance">
			<header>
				<identifier>oai:icce-ojs-tamu.tdl.org:article/8680</identifier>
				<datestamp>2020-06-23T01:34:57Z</datestamp>
				<setSpec>icce:Sediment</setSpec>
			</header>
			<metadata>
<oai_dc:dc xmlns:oai_dc="http://www.openarchives.org/OAI/2.0/oai_dc/" xmlns:dc="http://purl.org/dc/elements/1.1/" xmlns:xsi="http://www.w3.org/2001/XMLSchema-instance" xsi:schemaLocation="http://www.openarchives.org/OAI/2.0/oai_dc/  http://www.openarchives.org/OAI/2.0/oai_dc.xsd">
	<dc:title xml:lang="en">EVOLUTION OF NOBIRU COAST AT DECADAL TO CENTENNIAL SCALES INCLUDING THE 2011 TSUNAMI IMPACT</dc:title>
	<dc:creator xml:lang="en">Tanaka, Hitoshi</dc:creator>
	<dc:creator xml:lang="en">Tinh, Nguyen Xuan</dc:creator>
	<dc:creator xml:lang="en">Hoang, Vo Cong</dc:creator>
	<dc:description xml:lang="en">Nobiru Coast, which is 2.8 km long coast located in Miyagi Prefecture, Japan, is a well-known coast because of high sediment deposition rate (Figure 1). The predominant littoral drift of this coast is from east to west (Takahashi and Tanaka, 2005). The sediment deposit at the western end causes significant effect on the aquaculture in Matsushima Bay which is located on the right of Miyato Island, due to closure of a channel connecting open sea and Matsushima Bay. Tanaka et al. (2006) reported the sediment deposition rate on this coast from historical maps. The tsunami, which occurred on 11 March 2011, caused different types of damage on the left and right-hand sides of the coast. Accordingly, this study would evaluate the change of shoreline on Nobiru Coast at decadal to centennial scales including the 2011 tsunami impact using aerial and satellites images.</dc:description>
	<dc:publisher xml:lang="en">Coastal Engineering Research Council</dc:publisher>
	<dc:date>2018-12-30</dc:date>
	<dc:type>info:eu-repo/semantics/article</dc:type>
	<dc:type>info:eu-repo/semantics/publishedVersion</dc:type>
	<dc:format>application/pdf</dc:format>
	<dc:format>application/pdf</dc:format>
	<dc:identifier>https://icce-ojs-tamu.tdl.org/icce/article/view/8680</dc:identifier>
	<dc:identifier>10.9753/icce.v36.sediment.16</dc:identifier>
	<dc:source xml:lang="en">Coastal Engineering Proceedings; No. 36 (2018): Proceedings of 36th Conference on Coastal Engineering, Baltimore, Maryland, 2018; sediment.16</dc:source>
	<dc:source>2156-1028</dc:source>
	<dc:source>0589-087X</dc:source>
	<dc:language>eng</dc:language>
	<dc:relation>https://icce-ojs-tamu.tdl.org/icce/article/view/8680/7484</dc:relation>
	<dc:relation>https://icce-ojs-tamu.tdl.org/icce/article/view/8680/8064</dc:relation>
	<dc:rights xml:lang="en">Copyright (c) 2019 Coastal Engineering Proceedings</dc:rights>
</oai_dc:dc>
			</metadata>
		</record>
		
