<?xml version='1.0' encoding='utf-8'?>
<record xmlns="http://www.openarchives.org/OAI/2.0/" xmlns:xsi="http://www.w3.org/2001/XMLSchema-instance">
			<header>
				<identifier>oai:icce-ojs-tamu.tdl.org:article/8472</identifier>
				<datestamp>2020-06-23T01:34:57Z</datestamp>
				<setSpec>icce:Swash</setSpec>
			</header>
			<metadata>
<oai_dc:dc xmlns:oai_dc="http://www.openarchives.org/OAI/2.0/oai_dc/" xmlns:dc="http://purl.org/dc/elements/1.1/" xmlns:xsi="http://www.w3.org/2001/XMLSchema-instance" xsi:schemaLocation="http://www.openarchives.org/OAI/2.0/oai_dc/  http://www.openarchives.org/OAI/2.0/oai_dc.xsd">
	<dc:title xml:lang="en">TSUNAMI INUNDATION SIMULATIONS IN URBAN TOPOGRAPHY</dc:title>
	<dc:creator xml:lang="en">Miyashita, Takuya</dc:creator>
	<dc:creator xml:lang="en">Mori, Nobuhito</dc:creator>
	<dc:description xml:lang="en">The inundation of the 2011 Tohoku Earthquake Tsunami showed complex behavior over the land. According to the surveys of the Tohoku Earthquake Tsunami in 2011, the behavior of tsunami in urban areas was different from that in rural areas and the damage was not only dependent on the inundation heights but also the local momentum. The buildings are commonly excluded and smoothed off in the topography in the conventional inundation simulation but it's important to understand the local characteristics of tsunami run-up in urban areas. The purpose of this study is to understand and validate numerical models of tsunami in the urban area.</dc:description>
	<dc:publisher xml:lang="en">Coastal Engineering Research Council</dc:publisher>
	<dc:date>2018-12-30</dc:date>
	<dc:type>info:eu-repo/semantics/article</dc:type>
	<dc:type>info:eu-repo/semantics/publishedVersion</dc:type>
	<dc:format>application/pdf</dc:format>
	<dc:format>application/pdf</dc:format>
	<dc:identifier>https://icce-ojs-tamu.tdl.org/icce/article/view/8472</dc:identifier>
	<dc:identifier>10.9753/icce.v36.currents.62</dc:identifier>
	<dc:source xml:lang="en">Coastal Engineering Proceedings; No. 36 (2018): Proceedings of 36th Conference on Coastal Engineering, Baltimore, Maryland, 2018; currents.62</dc:source>
	<dc:source>2156-1028</dc:source>
	<dc:source>0589-087X</dc:source>
	<dc:language>eng</dc:language>
	<dc:relation>https://icce-ojs-tamu.tdl.org/icce/article/view/8472/7275</dc:relation>
	<dc:relation>https://icce-ojs-tamu.tdl.org/icce/article/view/8472/7906</dc:relation>
	<dc:rights xml:lang="en">Copyright (c) 2019 Coastal Engineering Proceedings</dc:rights>
</oai_dc:dc>
			</metadata>
		</record>
		
