<?xml version='1.0' encoding='utf-8'?>
<record xmlns="http://www.openarchives.org/OAI/2.0/" xmlns:xsi="http://www.w3.org/2001/XMLSchema-instance">
			<header>
				<identifier>oai:icce-ojs-tamu.tdl.org:article/4206</identifier>
				<datestamp>2021-01-19T19:19:49Z</datestamp>
				<setSpec>icce:old_proceedings</setSpec>
			</header>
			<metadata>
<oai_dc:dc xmlns:oai_dc="http://www.openarchives.org/OAI/2.0/oai_dc/" xmlns:dc="http://purl.org/dc/elements/1.1/" xmlns:xsi="http://www.w3.org/2001/XMLSchema-instance" xsi:schemaLocation="http://www.openarchives.org/OAI/2.0/oai_dc/  http://www.openarchives.org/OAI/2.0/oai_dc.xsd">
	<dc:title xml:lang="en">IRREGULAR WAVE TRANSFORMATION IN A BOUSSINESO WAVE MODEL</dc:title>
	<dc:creator xml:lang="en">Pruser, H.H.</dc:creator>
	<dc:creator xml:lang="en">Schaper, H.</dc:creator>
	<dc:creator xml:lang="en">Zielke, W.</dc:creator>
	<dc:subject xml:lang="en">Boussinesq model</dc:subject>
	<dc:subject xml:lang="en">irregular wave</dc:subject>
	<dc:subject xml:lang="en">wave transformation</dc:subject>
	<dc:description xml:lang="en">Numerical wave models for shallow water waves are of particular importance for the calculation of the wave climate in harbours and coastal areas. Especially nonlinear time domain models, which are based on the Boussinesq-Wave- Equations, may be helpful in the future for simulating the interaction of currents with refraction, diffraction, reflection and for simulating shoaling..-of irregular waves in natural areas; a potential which has not yet been fully developed. During the last ten years numerical models, based on these equations, have been published; such as ABBOTT et. al. , HAUGUEL and SCHAPER / ZIELKE . Research on this topic is currently being carried on. Some efforts have been made to verify the capability of the models to describe the various physical phenomena. However, up to now, verification has been limited to regular waves. The aim of this paper therefore is, to consider questions concerning irregular, nonlinear waves.</dc:description>
	<dc:publisher xml:lang="en">Coastal Engineering Research Council</dc:publisher>
	<dc:date>1986-01-29</dc:date>
	<dc:type>info:eu-repo/semantics/article</dc:type>
	<dc:type>info:eu-repo/semantics/publishedVersion</dc:type>
	<dc:format>application/pdf</dc:format>
	<dc:identifier>https://icce-ojs-tamu.tdl.org/icce/article/view/4206</dc:identifier>
	<dc:identifier>10.9753/icce.v20.205</dc:identifier>
	<dc:source xml:lang="en">Coastal Engineering Proceedings; No. 20 (1986): Proceedings of 20th Conference on Coastal Engineering, Taipei, Taiwan, 1986.; 205</dc:source>
	<dc:source>2156-1028</dc:source>
	<dc:source>0589-087X</dc:source>
	<dc:language>eng</dc:language>
	<dc:relation>https://icce-ojs-tamu.tdl.org/icce/article/view/4206/3887</dc:relation>
</oai_dc:dc>
			</metadata>
		</record>
		
