<?xml version='1.0' encoding='utf-8'?>
<record xmlns="http://www.openarchives.org/OAI/2.0/" xmlns:xsi="http://www.w3.org/2001/XMLSchema-instance">
			<header>
				<identifier>oai:bovine-ojs-tamu.tdl.org:article/4728</identifier>
				<datestamp>2020-02-15T08:42:38Z</datestamp>
				<setSpec>aabp:RS2</setSpec>
			</header>
			<metadata>
<oai_dc:dc xmlns:oai_dc="http://www.openarchives.org/OAI/2.0/oai_dc/" xmlns:dc="http://purl.org/dc/elements/1.1/" xmlns:xsi="http://www.w3.org/2001/XMLSchema-instance" xsi:schemaLocation="http://www.openarchives.org/OAI/2.0/oai_dc/  http://www.openarchives.org/OAI/2.0/oai_dc.xsd">
	<dc:title xml:lang="en">Relationship of Teat-end Hyperkeratosis to Incidence of Clinical Mastitis and Composite Milk Somatic Cell Count in a Large Holstein Dairy Herd with an Environmental Mastitis Problem</dc:title>
	<dc:creator xml:lang="en">Kasravi, R.</dc:creator>
	<dc:creator xml:lang="en">Bolourchi, M.</dc:creator>
	<dc:subject xml:lang="en">teat-end hyperkeratosis</dc:subject>
	<dc:subject xml:lang="en">mastitis</dc:subject>
	<dc:subject xml:lang="en">callosity thickness</dc:subject>
	<dc:subject xml:lang="en">Escherichia coli mastitis</dc:subject>
	<dc:description xml:lang="en">Several studies have demonstrated a positive association between teat-end hyperkeratosis (TEHK) and subclinical or clinical mastitis. Some studies found no positive correlation between them. To the knowledge of the authors, there is only one longitudinal study which demonstrated a negative association between teat-end callosity thickness and clinical Escherichia coli mastitis (Neijenhuis et al, 2001). The objective of this study was to determine whether TEHK is associated with an increased risk of clinical or subclinical mastitis in a large Holstein dairy herd in Tehran province of Iran, in which the monthly incidence rate of clinical mastitis was 9% prior to the beginning of the study.</dc:description>
	<dc:publisher xml:lang="en">American Association of Bovine Practitioners</dc:publisher>
	<dc:date>2006-09-21</dc:date>
	<dc:type>info:eu-repo/semantics/article</dc:type>
	<dc:type>info:eu-repo/semantics/publishedVersion</dc:type>
	<dc:format>application/pdf</dc:format>
	<dc:identifier>https://bovine-ojs-tamu.tdl.org/aabp/article/view/4728</dc:identifier>
	<dc:identifier>10.21423/aabppro20064728</dc:identifier>
	<dc:source xml:lang="en">American Association of Bovine Practitioners  Conference Proceedings; 2006; 248</dc:source>
	<dc:source>1079-9737</dc:source>
	<dc:language>eng</dc:language>
	<dc:relation>https://bovine-ojs-tamu.tdl.org/aabp/article/view/4728/4626</dc:relation>
	<dc:rights xml:lang="en">Copyright (c) 2006 American Association of Bovine Practitioners</dc:rights>
</oai_dc:dc>
			</metadata>
		</record>
		
